nextflow/__init__.py
nextflow/command.py
nextflow/exceptions.py
nextflow/io.py
nextflow/log.py
nextflow/models.py
nextflow/outputs.py
nextflowpy-0.12.0.dist-info/licenses/LICENSE
nextflowpy-0.12.0.dist-info/METADATA
nextflowpy-0.12.0.dist-info/WHEEL
nextflowpy-0.12.0.dist-info/top_level.txt
nextflowpy-0.12.0.dist-info/RECORD
