Metadata-Version: 2.4
Name: nextflowpy
Version: 0.12.0
Summary: A Python wrapper around Nextflow.
Home-page: https://github.com/goodwright/nextflow.py
Author: Sam Ireland
Author-email: sam@goodwright.com
License: GPLv3+
Keywords: nextflow bioinformatics pipeline
Classifier: Development Status :: 4 - Beta
Classifier: Topic :: Internet :: WWW/HTTP
Classifier: Intended Audience :: Developers
Classifier: License :: OSI Approved :: GNU General Public License v3 or later (GPLv3+)
Classifier: Topic :: Scientific/Engineering :: Bio-Informatics
Classifier: Programming Language :: Python :: 3
Classifier: Programming Language :: Python :: 3.10
Classifier: Programming Language :: Python :: 3.11
Classifier: Programming Language :: Python :: 3.12
Classifier: Programming Language :: Python :: 3.13
Requires-Python: !=2.*, !=3.0.*, !=3.1.*, !=3.2.*, !=3.3.*, !=3.4.*, !=3.5.*, !=3.6.*, !=3.7.*, !=3.8.*
License-File: LICENSE
Dynamic: author
Dynamic: author-email
Dynamic: classifier
Dynamic: description
Dynamic: description-content-type
Dynamic: home-page
Dynamic: keywords
Dynamic: license
Dynamic: license-file
Dynamic: requires-python
Dynamic: summary
